topsis_pkg/__init__.py
topsis_pkg/topsis.py
Topsis_Kritik_102203771-0.1.0.dist-info/LICENSE
Topsis_Kritik_102203771-0.1.0.dist-info/METADATA
Topsis_Kritik_102203771-0.1.0.dist-info/WHEEL
Topsis_Kritik_102203771-0.1.0.dist-info/entry_points.txt
Topsis_Kritik_102203771-0.1.0.dist-info/top_level.txt
Topsis_Kritik_102203771-0.1.0.dist-info/RECORD
