Metadata-Version: 2.2
Name: Topsis-Kritik-102203771
Version: 0.1.0
Summary: TOPSIS implementation for multiple-criteria decision analysis
Home-page: https://github.com/krbok/topsis
Author: Kritik
Author-email: your.email@example.com
Classifier: Programming Language :: Python :: 3
Classifier: License :: OSI Approved :: MIT License
Classifier: Operating System :: OS Independent
Requires-Python: >=3.6
License-File: LICENSE
Requires-Dist: pandas
Requires-Dist: numpy
